pyapi/server/__init__.py
pyapi/server/py.typed
pyapi/server/spec.py
pyapi/server/validation.py
pyapi_server-0.9.0.dist-info/METADATA
pyapi_server-0.9.0.dist-info/WHEEL
pyapi_server-0.9.0.dist-info/entry_points.txt
pyapi_server-0.9.0.dist-info/RECORD
