Metadata-Version: 2.1
Name: pyapi-server
Version: 0.9.0
Summary: Lightweight API framework using an OpenAPI spec for routing and validation.
Author-Email: Berislav Lopac <berislav@lopac.net>
License: MIT
Project-URL: homepage, https://pyapi-server.readthedocs.io
Project-URL: documentation, https://pyapi-server.readthedocs.io
Project-URL: repository, https://github.com/berislavlopac/pyapi-server
Requires-Python: >=3.9
Requires-Dist: PyYAML>=6.0.1
Requires-Dist: openapi-core>=0.19.1
Requires-Dist: starlette>=0.37.2
Requires-Dist: jsonschema-path>=0.3.2
Requires-Dist: stringcase>=1.2.0
Provides-Extra: uvicorn
Requires-Dist: uvicorn>=0.18.3; extra == "uvicorn"
Provides-Extra: docs
Requires-Dist: mkdocs>=1.3.0; extra == "docs"
Requires-Dist: mkdocs-material>=9.5.17; extra == "docs"
